wipac_telemetry/__init__.py
wipac_telemetry/py.typed
wipac_telemetry/tracing_tools/__init__.py
wipac_telemetry/tracing_tools/config.py
wipac_telemetry/tracing_tools/events.py
wipac_telemetry/tracing_tools/propagations.py
wipac_telemetry/tracing_tools/spans.py
wipac_telemetry/tracing_tools/utils.py
wipac_telemetry-0.3.1.dist-info/LICENSE
wipac_telemetry-0.3.1.dist-info/METADATA
wipac_telemetry-0.3.1.dist-info/WHEEL
wipac_telemetry-0.3.1.dist-info/top_level.txt
wipac_telemetry-0.3.1.dist-info/RECORD
