Metadata-Version: 2.1
Name: wipac-telemetry
Version: 0.3.1
Summary: WIPAC Telemetry: Monitoring/Tracing Applications, Supporting Infrastructures, and Services
Home-page: https://github.com/WIPACrepo/wipac-telemetry
Download-URL: https://pypi.org/project/wipac-telemetry/
Author: WIPAC Developers
Author-email: developers@icecube.wisc.edu
License: MIT
Project-URL: Tracker, https://github.com/WIPACrepo/wipac-telemetry/issues
Project-URL: Source, https://github.com/WIPACrepo/wipac-telemetry
Keywords: python,tools,utilities,OpenTelemetry,tracing,telemetry,WIPAC,IceCube
Classifier: Development Status :: 4 - Beta
Classifier: License :: OSI Approved :: MIT License
Classifier: Programming Language :: Python :: 3.8
Classifier: Programming Language :: Python :: 3.9
Classifier: Programming Language :: Python :: 3.10
Classifier: Programming Language :: Python :: 3.11
Classifier: Programming Language :: Python :: 3.12
Classifier: Programming Language :: Python :: 3.13
Requires-Python: <3.14,>=3.8
License-File: LICENSE
Requires-Dist: coloredlogs
Requires-Dist: opentelemetry-api
Requires-Dist: opentelemetry-exporter-jaeger
Requires-Dist: opentelemetry-exporter-otlp-proto-http
Requires-Dist: opentelemetry-sdk
Requires-Dist: protobuf
Requires-Dist: typing-extensions
Requires-Dist: wipac-dev-tools
Provides-Extra: dev
Requires-Dist: opentelemetry-instrumentation-flask; extra == "dev"
Requires-Dist: opentelemetry-instrumentation-requests; extra == "dev"
Requires-Dist: opentelemetry-exporter-otlp==1.6.2; extra == "dev"
Requires-Dist: opentelemetry-exporter-otlp-proto-grpc==1.6.2; extra == "dev"
Requires-Dist: opentelemetry-propagator-b3==1.6.2; extra == "dev"
Requires-Dist: pika; extra == "dev"
